{
  "lines": [
    {
      "t": 31.8,
      "text": "There's a hum in the walls and it knows my name,",
      "words": [
        {
          "t": 31.8,
          "d": 1.092921052631579,
          "w": "There's"
        },
        {
          "t": 33.13487528344671,
          "d": 0.1561315789473684,
          "w": "a"
        },
        {
          "t": 33.13487528344671,
          "d": 0.46839473684210525,
          "w": "hum"
        },
        {
          "t": 33.82052631578947,
          "d": 0.3122631578947368,
          "w": "in"
        },
        {
          "t": 34.187894736842104,
          "d": 0.46839473684210525,
          "w": "the"
        },
        {
          "t": 34.73894736842105,
          "d": 0.7806578947368421,
          "w": "walls"
        },
        {
          "t": 35.65736842105263,
          "d": 0.46839473684210525,
          "w": "and"
        },
        {
          "t": 36.20842105263158,
          "d": 0.3122631578947368,
          "w": "it"
        },
        {
          "t": 36.57578947368421,
          "d": 0.7806578947368421,
          "w": "knows"
        },
        {
          "t": 37.50022675736962,
          "d": 0.3122631578947368,
          "w": "my"
        },
        {
          "t": 37.86157894736842,
          "d": 0.7806578947368421,
          "w": "name,"
        }
      ]
    },
    {
      "t": 38.638004535147395,
      "text": "every room I walk in sounds exactly the same.",
      "words": [
        {
          "t": 38.638004535147395,
          "d": 0.8522972972972974,
          "w": "every"
        },
        {
          "t": 39.78270270270271,
          "d": 0.681837837837838,
          "w": "room"
        },
        {
          "t": 40.49560090702948,
          "d": 0.1704594594594595,
          "w": "I"
        },
        {
          "t": 40.78540540540541,
          "d": 0.681837837837838,
          "w": "walk"
        },
        {
          "t": 41.587567567567575,
          "d": 0.340918918918919,
          "w": "in"
        },
        {
          "t": 41.988648648648656,
          "d": 1.022756756756757,
          "w": "sounds"
        },
        {
          "t": 43.281995464852606,
          "d": 1.1932162162162165,
          "w": "exactly"
        },
        {
          "t": 44.595675675675686,
          "d": 0.5113783783783785,
          "w": "the"
        },
        {
          "t": 45.139591836734695,
          "d": 0.8522972972972974,
          "w": "same."
        }
      ]
    },
    {
      "t": 46.068390022675736,
      "text": "Quarter century of ghosts harmonizing in the dark,",
      "words": [
        {
          "t": 46.068390022675736,
          "d": 0.9464651162790693,
          "w": "Quarter"
        },
        {
          "t": 47.313488372093026,
          "d": 0.9464651162790693,
          "w": "century"
        },
        {
          "t": 48.39038548752835,
          "d": 0.27041860465116263,
          "w": "of"
        },
        {
          "t": 48.854784580498865,
          "d": 0.8112558139534879,
          "w": "ghosts"
        },
        {
          "t": 49.80680272108844,
          "d": 1.4873023255813946,
          "w": "harmonizing"
        },
        {
          "t": 51.44930232558139,
          "d": 0.27041860465116263,
          "w": "in"
        },
        {
          "t": 51.61795918367347,
          "d": 0.40562790697674395,
          "w": "the"
        },
        {
          "t": 52.10557823129252,
          "d": 0.6760465116279066,
          "w": "dark,"
        }
      ]
    },
    {
      "t": 53.04,
      "text": "Been carrying this frequency since you were learning to park.",
      "words": [
        {
          "t": 53.04,
          "d": 0.6970000000000002,
          "w": "Been"
        },
        {
          "t": 53.823854875283445,
          "d": 1.3940000000000003,
          "w": "carrying"
        },
        {
          "t": 55.5,
          "d": 0.6970000000000002,
          "w": "this"
        },
        {
          "t": 56.42448979591837,
          "d": 1.5682500000000006,
          "w": "frequency"
        },
        {
          "t": 58.142766439909295,
          "d": 0.8712500000000003,
          "w": "since"
        },
        {
          "t": 59.187664399092974,
          "d": 0.5227500000000002,
          "w": "you"
        },
        {
          "t": 59.805,
          "d": 0.6970000000000002,
          "w": "were"
        },
        {
          "t": 60.625,
          "d": 1.3940000000000003,
          "w": "learning"
        },
        {
          "t": 62.265,
          "d": 0.3485000000000001,
          "w": "to"
        },
        {
          "t": 62.76353741496599,
          "d": 0.8712500000000003,
          "w": "park."
        }
      ]
    },
    {
      "t": 63.7,
      "text": "The static used to scare me, now it's all I want to hear",
      "words": [
        {
          "t": 63.7,
          "d": 0.20168181818181838,
          "w": "The"
        },
        {
          "t": 63.93727272727273,
          "d": 0.40336363636363676,
          "w": "static"
        },
        {
          "t": 64.27283446712018,
          "d": 0.2689090909090912,
          "w": "used"
        },
        {
          "t": 64.72818181818181,
          "d": 0.1344545454545456,
          "w": "to"
        },
        {
          "t": 64.88636363636363,
          "d": 0.336136363636364,
          "w": "scare"
        },
        {
          "t": 65.28181818181817,
          "d": 0.20168181818181838,
          "w": "me,"
        },
        {
          "t": 65.51909090909089,
          "d": 0.20168181818181838,
          "w": "now"
        },
        {
          "t": 65.78213151927437,
          "d": 0.2689090909090912,
          "w": "it's"
        },
        {
          "t": 66.07272727272725,
          "d": 0.20168181818181838,
          "w": "all"
        },
        {
          "t": 66.45551020408163,
          "d": 0.0672272727272728,
          "w": "I"
        },
        {
          "t": 66.45551020408163,
          "d": 0.2689090909090912,
          "w": "want"
        },
        {
          "t": 66.75736961451247,
          "d": 0.1344545454545456,
          "w": "to"
        },
        {
          "t": 66.75736961451247,
          "d": 0.2689090909090912,
          "w": "hear"
        }
      ]
    },
    {
      "t": 67.18,
      "text": "put me up on the pulpit, let me make my message clear.",
      "words": [
        {
          "t": 67.18,
          "d": 0.09844186046511608,
          "w": "put"
        },
        {
          "t": 67.29581395348838,
          "d": 0.06562790697674405,
          "w": "me"
        },
        {
          "t": 67.37302325581396,
          "d": 0.06562790697674405,
          "w": "up"
        },
        {
          "t": 67.45023255813955,
          "d": 0.06562790697674405,
          "w": "on"
        },
        {
          "t": 67.52744186046513,
          "d": 0.09844186046511608,
          "w": "the"
        },
        {
          "t": 67.6432558139535,
          "d": 0.22969767441860417,
          "w": "pulpit,"
        },
        {
          "t": 68.01124716553288,
          "d": 0.09844186046511608,
          "w": "let"
        },
        {
          "t": 68.01124716553288,
          "d": 0.06562790697674405,
          "w": "me"
        },
        {
          "t": 68.01124716553288,
          "d": 0.1312558139534881,
          "w": "make"
        },
        {
          "t": 68.31310657596372,
          "d": 0.06562790697674405,
          "w": "my"
        },
        {
          "t": 68.31310657596372,
          "d": 0.22969767441860417,
          "w": "message"
        },
        {
          "t": 68.60837209302328,
          "d": 0.19688372093023215,
          "w": "clear."
        }
      ]
    },
    {
      "t": 68.84,
      "text": "I don't need your platform, I don't need your stage,",
      "words": [
        {
          "t": 68.84,
          "d": 0.10713953488372095,
          "w": "I"
        },
        {
          "t": 68.96604651162791,
          "d": 0.5356976744186048,
          "w": "don't"
        },
        {
          "t": 69.59627906976745,
          "d": 0.4285581395348838,
          "w": "need"
        },
        {
          "t": 70.12426303854875,
          "d": 0.4285581395348838,
          "w": "your"
        },
        {
          "t": 70.60465116279072,
          "d": 0.9642558139534888,
          "w": "platform,"
        },
        {
          "t": 71.73906976744188,
          "d": 0.10713953488372095,
          "w": "I"
        },
        {
          "t": 71.86511627906978,
          "d": 0.5356976744186048,
          "w": "don't"
        },
        {
          "t": 72.49534883720932,
          "d": 0.4285581395348838,
          "w": "need"
        },
        {
          "t": 72.98031746031747,
          "d": 0.4285581395348838,
          "w": "your"
        },
        {
          "t": 73.53759637188209,
          "d": 0.6428372093023258,
          "w": "stage,"
        }
      ]
    },
    {
      "t": 74.3502947845805,
      "text": "I built you a cathedral and now im turning the page",
      "words": [
        {
          "t": 74.3502947845805,
          "d": 0.055146341463414565,
          "w": "I"
        },
        {
          "t": 74.3502947845805,
          "d": 0.2757317073170728,
          "w": "built"
        },
        {
          "t": 74.64926829268293,
          "d": 0.16543902439024366,
          "w": "you"
        },
        {
          "t": 74.81469387755102,
          "d": 0.055146341463414565,
          "w": "a"
        },
        {
          "t": 74.95401360544219,
          "d": 0.4963170731707311,
          "w": "cathedral"
        },
        {
          "t": 75.49268292682926,
          "d": 0.16543902439024366,
          "w": "and"
        },
        {
          "t": 75.72027210884355,
          "d": 0.16543902439024366,
          "w": "now"
        },
        {
          "t": 75.88195121951217,
          "d": 0.11029268292682913,
          "w": "im"
        },
        {
          "t": 76.01170731707315,
          "d": 0.38602439024390195,
          "w": "turning"
        },
        {
          "t": 76.46585365853656,
          "d": 0.16543902439024366,
          "w": "the"
        },
        {
          "t": 76.66048780487802,
          "d": 0.22058536585365826,
          "w": "page"
        }
      ]
    },
    {
      "t": 76.92,
      "text": "Stone by stone, brick by brick,",
      "words": [
        {
          "t": 76.92,
          "d": 0.47076923076923005,
          "w": "Stone"
        },
        {
          "t": 77.60108843537415,
          "d": 0.18830769230769204,
          "w": "by"
        },
        {
          "t": 77.60108843537415,
          "d": 0.5649230769230761,
          "w": "stone,"
        },
        {
          "t": 78.36,
          "d": 0.47076923076923005,
          "w": "brick"
        },
        {
          "t": 78.91384615384615,
          "d": 0.18830769230769204,
          "w": "by"
        },
        {
          "t": 79.20326530612245,
          "d": 0.5649230769230761,
          "w": "brick,"
        }
      ]
    },
    {
      "t": 79.6908843537415,
      "text": "whispers of infinity, let em rip.",
      "words": [
        {
          "t": 79.6908843537415,
          "d": 0.884,
          "w": "whispers"
        },
        {
          "t": 80.84,
          "d": 0.221,
          "w": "of"
        },
        {
          "t": 81.10000000000001,
          "d": 0.9945000000000003,
          "w": "infinity,"
        },
        {
          "t": 82.12897959183674,
          "d": 0.3315,
          "w": "let"
        },
        {
          "t": 82.66000000000001,
          "d": 0.221,
          "w": "em"
        },
        {
          "t": 82.8952380952381,
          "d": 0.442,
          "w": "rip."
        }
      ]
    },
    {
      "t": 83.44,
      "text": "Twenty-five years ive been holding my tongue",
      "words": [
        {
          "t": 83.44,
          "d": 0.8611842105263157,
          "w": "Twenty-five"
        },
        {
          "t": 84.45315789473683,
          "d": 0.3914473684210526,
          "w": "years"
        },
        {
          "t": 84.98503401360544,
          "d": 0.23486842105263156,
          "w": "ive"
        },
        {
          "t": 85.24045351473923,
          "d": 0.3131578947368421,
          "w": "been"
        },
        {
          "t": 85.55842105263157,
          "d": 0.5480263157894737,
          "w": "holding"
        },
        {
          "t": 86.23891156462585,
          "d": 0.15657894736842104,
          "w": "my"
        },
        {
          "t": 86.23891156462585,
          "d": 0.4697368421052631,
          "w": "tongue"
        }
      ]
    },
    {
      "t": 87.02839002267574,
      "text": "now every word hits like a kick to a drum.",
      "words": [
        {
          "t": 87.02839002267574,
          "d": 1.466636363636364,
          "w": "now"
        },
        {
          "t": 88.70022675736962,
          "d": 2.44439393939394,
          "w": "every"
        },
        {
          "t": 91.54121212121211,
          "d": 1.9555151515151519,
          "w": "word"
        },
        {
          "t": 93.78539682539683,
          "d": 1.9555151515151519,
          "w": "hits"
        },
        {
          "t": 96.14242424242423,
          "d": 1.9555151515151519,
          "w": "like"
        },
        {
          "t": 98.44303030303028,
          "d": 0.48887878787878797,
          "w": "a"
        },
        {
          "t": 99.0181818181818,
          "d": 1.9555151515151519,
          "w": "kick"
        },
        {
          "t": 101.16934240362812,
          "d": 0.9777575757575759,
          "w": "to"
        },
        {
          "t": 102.4690909090909,
          "d": 0.48887878787878797,
          "w": "a"
        },
        {
          "t": 103.04424242424241,
          "d": 2.44439393939394,
          "w": "drum."
        }
      ]
    },
    {
      "t": 105.92,
      "text": "I can hear the songs in my head,",
      "words": [
        {
          "t": 105.92,
          "d": 0.07819999999999991,
          "w": "I"
        },
        {
          "t": 106.012,
          "d": 0.23459999999999967,
          "w": "can"
        },
        {
          "t": 106.288,
          "d": 0.31279999999999963,
          "w": "hear"
        },
        {
          "t": 106.65599999999999,
          "d": 0.23459999999999967,
          "w": "the"
        },
        {
          "t": 106.93199999999999,
          "d": 0.3909999999999995,
          "w": "songs"
        },
        {
          "t": 107.27619047619048,
          "d": 0.15639999999999982,
          "w": "in"
        },
        {
          "t": 107.57599999999998,
          "d": 0.15639999999999982,
          "w": "my"
        },
        {
          "t": 107.75999999999998,
          "d": 0.3909999999999995,
          "w": "head,"
        }
      ]
    },
    {
      "t": 108.22,
      "text": "spinning around with all the words that I've read,",
      "words": [
        {
          "t": 108.22,
          "d": 0.29790476190476245,
          "w": "spinning"
        },
        {
          "t": 108.57047619047619,
          "d": 0.22342857142857184,
          "w": "around"
        },
        {
          "t": 108.83333333333333,
          "d": 0.14895238095238122,
          "w": "with"
        },
        {
          "t": 109.00857142857143,
          "d": 0.11171428571428592,
          "w": "all"
        },
        {
          "t": 109.14,
          "d": 0.11171428571428592,
          "w": "the"
        },
        {
          "t": 109.27142857142857,
          "d": 0.18619047619047652,
          "w": "words"
        },
        {
          "t": 109.49047619047619,
          "d": 0.14895238095238122,
          "w": "that"
        },
        {
          "t": 109.80716553287982,
          "d": 0.14895238095238122,
          "w": "I've"
        },
        {
          "t": 109.80716553287982,
          "d": 0.18619047619047652,
          "w": "read,"
        }
      ]
    },
    {
      "t": 110.06,
      "text": "mixing about with everything that they've said,",
      "words": [
        {
          "t": 110.06,
          "d": 0.2313658536585365,
          "w": "mixing"
        },
        {
          "t": 110.33219512195122,
          "d": 0.1928048780487804,
          "w": "about"
        },
        {
          "t": 110.5590243902439,
          "d": 0.15424390243902433,
          "w": "with"
        },
        {
          "t": 110.82884353741497,
          "d": 0.3856097560975608,
          "w": "everything"
        },
        {
          "t": 111.19414634146342,
          "d": 0.15424390243902433,
          "w": "that"
        },
        {
          "t": 111.37560975609757,
          "d": 0.26992682926829265,
          "w": "they've"
        },
        {
          "t": 111.69317073170733,
          "d": 0.1928048780487804,
          "w": "said,"
        }
      ]
    },
    {
      "t": 111.92,
      "text": "but I'm afraid that you've all been misled",
      "words": [
        {
          "t": 111.92,
          "d": 0.1267714285714282,
          "w": "but"
        },
        {
          "t": 112.06914285714286,
          "d": 0.1267714285714282,
          "w": "I'm"
        },
        {
          "t": 112.21828571428573,
          "d": 0.2535428571428564,
          "w": "afraid"
        },
        {
          "t": 112.45424036281179,
          "d": 0.16902857142857092,
          "w": "that"
        },
        {
          "t": 112.71542857142857,
          "d": 0.2535428571428564,
          "w": "you've"
        },
        {
          "t": 113.01371428571429,
          "d": 0.1267714285714282,
          "w": "all"
        },
        {
          "t": 113.16285714285715,
          "d": 0.16902857142857092,
          "w": "been"
        },
        {
          "t": 113.36171428571429,
          "d": 0.2535428571428564,
          "w": "misled"
        }
      ]
    },
    {
      "t": 113.63845804988662,
      "text": "by all of the scrolling that you do from your bed.",
      "words": [
        {
          "t": 113.63845804988662,
          "d": 0.08075000000000025,
          "w": "by"
        },
        {
          "t": 113.87065759637188,
          "d": 0.12112500000000036,
          "w": "all"
        },
        {
          "t": 113.87065759637188,
          "d": 0.08075000000000025,
          "w": "of"
        },
        {
          "t": 114.10285714285715,
          "d": 0.12112500000000036,
          "w": "the"
        },
        {
          "t": 114.10285714285715,
          "d": 0.36337500000000106,
          "w": "scrolling"
        },
        {
          "t": 114.56249999999999,
          "d": 0.1615000000000005,
          "w": "that"
        },
        {
          "t": 114.75249999999998,
          "d": 0.12112500000000036,
          "w": "you"
        },
        {
          "t": 114.89499999999998,
          "d": 0.08075000000000025,
          "w": "do"
        },
        {
          "t": 114.98999999999998,
          "d": 0.1615000000000005,
          "w": "from"
        },
        {
          "t": 115.17999999999998,
          "d": 0.1615000000000005,
          "w": "your"
        },
        {
          "t": 115.33351473922903,
          "d": 0.1615000000000005,
          "w": "bed."
        }
      ]
    },
    {
      "t": 115.47283446712018,
      "text": "I was wide awake turning silence to thread,",
      "words": [
        {
          "t": 115.47283446712018,
          "d": 0.0420277777777778,
          "w": "I"
        },
        {
          "t": 115.47283446712018,
          "d": 0.1260833333333334,
          "w": "was"
        },
        {
          "t": 115.75777777777779,
          "d": 0.1681111111111112,
          "w": "wide"
        },
        {
          "t": 115.95555555555556,
          "d": 0.21013888888888904,
          "w": "awake"
        },
        {
          "t": 116.19265306122449,
          "d": 0.2941944444444446,
          "w": "turning"
        },
        {
          "t": 116.40163265306123,
          "d": 0.2941944444444446,
          "w": "silence"
        },
        {
          "t": 116.89500000000001,
          "d": 0.0840555555555556,
          "w": "to"
        },
        {
          "t": 116.9938888888889,
          "d": 0.2941944444444446,
          "w": "thread,"
        }
      ]
    },
    {
      "t": 117.34,
      "text": "fingers on the strings till my fingertips bled,",
      "words": [
        {
          "t": 117.34,
          "d": 0.3391500000000002,
          "w": "fingers"
        },
        {
          "t": 117.739,
          "d": 0.09690000000000004,
          "w": "on"
        },
        {
          "t": 117.85300000000001,
          "d": 0.14535000000000006,
          "w": "the"
        },
        {
          "t": 118.11990929705216,
          "d": 0.3391500000000002,
          "w": "strings"
        },
        {
          "t": 118.5146485260771,
          "d": 0.19380000000000008,
          "w": "till"
        },
        {
          "t": 118.70040816326531,
          "d": 0.09690000000000004,
          "w": "my"
        },
        {
          "t": 118.70040816326531,
          "d": 0.4845000000000002,
          "w": "fingertips"
        },
        {
          "t": 119.33500000000001,
          "d": 0.2422500000000001,
          "w": "bled,"
        }
      ]
    },
    {
      "t": 119.62,
      "text": "building something real while the algorithm fed",
      "words": [
        {
          "t": 119.62,
          "d": 0.9918048780487789,
          "w": "building"
        },
        {
          "t": 120.81342403628118,
          "d": 1.1157804878048763,
          "w": "something"
        },
        {
          "t": 122.22984126984127,
          "d": 0.49590243902438946,
          "w": "real"
        },
        {
          "t": 122.6829268292683,
          "d": 0.6198780487804867,
          "w": "while"
        },
        {
          "t": 123.41219512195123,
          "d": 0.371926829268292,
          "w": "the"
        },
        {
          "t": 123.84975609756098,
          "d": 1.1157804878048763,
          "w": "algorithm"
        },
        {
          "t": 125.20199546485262,
          "d": 0.371926829268292,
          "w": "fed"
        }
      ]
    },
    {
      "t": 125.6431746031746,
      "text": "you fifteen seconds of whatever kept you dead —",
      "words": [
        {
          "t": 125.6431746031746,
          "d": 0.46161538461538476,
          "w": "you"
        },
        {
          "t": 126.14307692307692,
          "d": 1.0771025641025644,
          "w": "fifteen"
        },
        {
          "t": 127.47755102040817,
          "d": 1.0771025641025644,
          "w": "seconds"
        },
        {
          "t": 128.5688888888889,
          "d": 0.30774358974358984,
          "w": "of"
        },
        {
          "t": 129.03948717948717,
          "d": 1.2309743589743594,
          "w": "whatever"
        },
        {
          "t": 130.4876923076923,
          "d": 0.6154871794871797,
          "w": "kept"
        },
        {
          "t": 131.21179487179487,
          "d": 0.46161538461538476,
          "w": "you"
        },
        {
          "t": 131.75487179487178,
          "d": 0.6154871794871797,
          "w": "dead"
        },
        {
          "t": 132.47897435897434,
          "d": 0.15387179487179492,
          "w": "—"
        }
      ]
    },
    {
      "t": 132.66,
      "text": "I chose the road but I cant help where it led.",
      "words": [
        {
          "t": 132.66,
          "d": 0.05950000000000024,
          "w": "I"
        },
        {
          "t": 132.73,
          "d": 0.2975000000000012,
          "w": "chose"
        },
        {
          "t": 133.07999999999998,
          "d": 0.1785000000000007,
          "w": "the"
        },
        {
          "t": 133.29,
          "d": 0.23800000000000096,
          "w": "road"
        },
        {
          "t": 133.57,
          "d": 0.1785000000000007,
          "w": "but"
        },
        {
          "t": 133.78,
          "d": 0.05950000000000024,
          "w": "I"
        },
        {
          "t": 133.85,
          "d": 0.23800000000000096,
          "w": "cant"
        },
        {
          "t": 134.13,
          "d": 0.23800000000000096,
          "w": "help"
        },
        {
          "t": 134.41,
          "d": 0.2975000000000012,
          "w": "where"
        },
        {
          "t": 134.76,
          "d": 0.11900000000000048,
          "w": "it"
        },
        {
          "t": 134.89999999999998,
          "d": 0.23800000000000096,
          "w": "led."
        }
      ]
    },
    {
      "t": 135.18,
      "text": "Stone by stone, brick by brick,",
      "words": [
        {
          "t": 135.18,
          "d": 2.5,
          "w": "Stone"
        },
        {
          "t": 143.61846153846153,
          "d": 2.5,
          "w": "by"
        },
        {
          "t": 147.0055328798186,
          "d": 2.5,
          "w": "stone,"
        },
        {
          "t": 157.11999999999998,
          "d": 2.5,
          "w": "brick"
        },
        {
          "t": 165.55846153846153,
          "d": 2.5,
          "w": "by"
        },
        {
          "t": 168.93384615384613,
          "d": 2.5,
          "w": "brick,"
        }
      ]
    },
    {
      "t": 179.06,
      "text": "whispers of infinity, let em rip.",
      "words": [
        {
          "t": 179.06,
          "d": 1.8748571428571423,
          "w": "whispers"
        },
        {
          "t": 181.2657142857143,
          "d": 0.4687142857142856,
          "w": "of"
        },
        {
          "t": 181.81714285714287,
          "d": 2.1092142857142857,
          "w": "infinity,"
        },
        {
          "t": 184.38965986394558,
          "d": 0.7030714285714283,
          "w": "let"
        },
        {
          "t": 185.1257142857143,
          "d": 0.4687142857142856,
          "w": "em"
        },
        {
          "t": 185.67714285714288,
          "d": 0.9374285714285712,
          "w": "rip."
        }
      ]
    },
    {
      "t": 186.7116553287982,
      "text": "Twenty-five years ive been holding my tongue",
      "words": [
        {
          "t": 186.7116553287982,
          "d": 0.7381578947368421,
          "w": "Twenty-five"
        },
        {
          "t": 187.6484210526316,
          "d": 0.3355263157894737,
          "w": "years"
        },
        {
          "t": 188.10485260770974,
          "d": 0.2013157894736842,
          "w": "ive"
        },
        {
          "t": 188.28,
          "d": 0.26842105263157895,
          "w": "been"
        },
        {
          "t": 188.63891156462586,
          "d": 0.4697368421052631,
          "w": "holding"
        },
        {
          "t": 189.10331065759638,
          "d": 0.13421052631578947,
          "w": "my"
        },
        {
          "t": 189.3063157894737,
          "d": 0.4026315789473684,
          "w": "tongue"
        }
      ]
    },
    {
      "t": 189.79990929705215,
      "text": "now every word hits like a kick to a drum.",
      "words": [
        {
          "t": 189.79990929705215,
          "d": 0.23181818181818178,
          "w": "now"
        },
        {
          "t": 189.9392290249433,
          "d": 0.3863636363636364,
          "w": "every"
        },
        {
          "t": 190.50727272727275,
          "d": 0.3090909090909091,
          "w": "word"
        },
        {
          "t": 190.87090909090912,
          "d": 0.3090909090909091,
          "w": "hits"
        },
        {
          "t": 191.14666666666668,
          "d": 0.3090909090909091,
          "w": "like"
        },
        {
          "t": 191.59818181818187,
          "d": 0.07727272727272727,
          "w": "a"
        },
        {
          "t": 191.7968253968254,
          "d": 0.3090909090909091,
          "w": "kick"
        },
        {
          "t": 192.05272727272734,
          "d": 0.15454545454545454,
          "w": "to"
        },
        {
          "t": 192.23454545454553,
          "d": 0.07727272727272727,
          "w": "a"
        },
        {
          "t": 192.32545454545462,
          "d": 0.3863636363636364,
          "w": "drum."
        }
      ]
    },
    {
      "t": 192.78,
      "text": "Stone by stone, brick by brick,",
      "words": [
        {
          "t": 192.78,
          "d": 0.4903846153846154,
          "w": "Stone"
        },
        {
          "t": 193.35692307692307,
          "d": 0.19615384615384615,
          "w": "by"
        },
        {
          "t": 193.5876923076923,
          "d": 0.5884615384615385,
          "w": "stone,"
        },
        {
          "t": 194.27999999999997,
          "d": 0.4903846153846154,
          "w": "brick"
        },
        {
          "t": 194.85692307692304,
          "d": 0.19615384615384615,
          "w": "by"
        },
        {
          "t": 195.09405895691611,
          "d": 0.5884615384615385,
          "w": "brick,"
        }
      ]
    },
    {
      "t": 195.78,
      "text": "whispers of infinity, let em rip.",
      "words": [
        {
          "t": 195.78,
          "d": 0.7285714285714285,
          "w": "whispers"
        },
        {
          "t": 196.63714285714286,
          "d": 0.18214285714285713,
          "w": "of"
        },
        {
          "t": 196.85877551020408,
          "d": 0.8196428571428572,
          "w": "infinity,"
        },
        {
          "t": 197.83401360544218,
          "d": 0.2732142857142857,
          "w": "let"
        },
        {
          "t": 198.15909297052156,
          "d": 0.18214285714285713,
          "w": "em"
        },
        {
          "t": 198.3514285714286,
          "d": 0.36428571428571427,
          "w": "rip."
        }
      ]
    },
    {
      "t": 198.78,
      "text": "Twenty-five years ive been holding my tongue",
      "words": [
        {
          "t": 198.78,
          "d": 0.7381578947368421,
          "w": "Twenty-five"
        },
        {
          "t": 199.6484210526316,
          "d": 0.3355263157894737,
          "w": "years"
        },
        {
          "t": 200.04315789473685,
          "d": 0.2013157894736842,
          "w": "ive"
        },
        {
          "t": 200.28,
          "d": 0.26842105263157895,
          "w": "been"
        },
        {
          "t": 200.59578947368422,
          "d": 0.4697368421052631,
          "w": "holding"
        },
        {
          "t": 201.10802721088436,
          "d": 0.13421052631578947,
          "w": "my"
        },
        {
          "t": 201.3063157894737,
          "d": 0.4026315789473684,
          "w": "tongue"
        }
      ]
    },
    {
      "t": 201.78,
      "text": "now every word hits like kick to a drum.",
      "words": [
        {
          "t": 201.78,
          "d": 0.31875,
          "w": "now"
        },
        {
          "t": 202.155,
          "d": 0.53125,
          "w": "every"
        },
        {
          "t": 202.78,
          "d": 0.425,
          "w": "word"
        },
        {
          "t": 203.22104308390024,
          "d": 0.425,
          "w": "hits"
        },
        {
          "t": 203.8247619047619,
          "d": 0.425,
          "w": "like"
        },
        {
          "t": 204.21950113378685,
          "d": 0.425,
          "w": "kick"
        },
        {
          "t": 204.77678004535147,
          "d": 0.2125,
          "w": "to"
        },
        {
          "t": 205.03,
          "d": 0.10625,
          "w": "a"
        },
        {
          "t": 205.19473922902495,
          "d": 0.53125,
          "w": "drum."
        }
      ]
    }
  ],
  "meta": {
    "source_canonical": "rr-1 - Clockwork Infinity.txt",
    "source_whisper": "rr-1 - Clockwork Infinity.whisper.json",
    "num_lines": 30,
    "num_words": 256,
    "matched_pct": 89.8,
    "healed_from_whisper_line_level": true,
    "healed_at": "2026-04-20T09:23:11.405731Z",
    "line_match_rate": "25/30"
  }
}